{
  "editor": {
    "allAngles": false,
    "entityTextureMode": false
  },
  "textureWidth": 8,
  "textureHeight": 8,
  "textureSizes": {
  },
  "textures": {
    "brambleberry": "wildcraftfruit:items/fruit/brambleberry"
  },
  "elements": [
    {
      "name": "origin",
      "from": [ 8.0, 0.0, 8.0 ],
      "to": [ 8.0, 0.0, 8.0 ],
      "rotationOrigin": [ 8.0, 0.0, 8.0 ],
      "faces": {
        "north": { "texture": "#brambleberry", "uv": [ 0.0, 0.0, 0.5, 0.5 ], "enabled": false },
        "east": { "texture": "#brambleberry", "uv": [ 0.0, 0.0, 0.5, 0.5 ], "enabled": false },
        "south": { "texture": "#brambleberry", "uv": [ 0.0, 0.0, 0.5, 0.5 ], "enabled": false },
        "west": { "texture": "#brambleberry", "uv": [ 0.0, 0.0, 0.5, 0.5 ], "enabled": false },
        "up": { "texture": "#brambleberry", "uv": [ 0.0, 0.0, 0.5, 0.5 ], "enabled": false },
        "down": { "texture": "#brambleberry", "uv": [ 0.0, 0.0, 0.5, 0.5 ], "enabled": false }
      },
      "children": [
        {
          "name": "body",
          "from": [ -1.7, 1.0, 0.2 ],
          "to": [ 1.3, 4.0, 3.2 ],
          "rotationOrigin": [ -0.2, 1.0, 1.7 ],
          "rotationX": -3.0,
          "rotationY": -90.0,
          "rotationZ": -45.0,
          "faces": {
            "north": { "texture": "#brambleberry", "uv": [ 0.0, 0.0, 3.0, 3.0 ] },
            "east": { "texture": "#brambleberry", "uv": [ 0.5, 0.0, 3.5, 3.0 ] },
            "south": { "texture": "#brambleberry", "uv": [ 0.5, 0.0, 3.5, 3.0 ] },
            "west": { "texture": "#brambleberry", "uv": [ 0.0, 0.0, 3.0, 3.0 ] },
            "up": { "texture": "#brambleberry", "uv": [ 0.5, 0.5, 3.5, 3.5 ] },
            "down": { "texture": "#brambleberry", "uv": [ 0.5, 0.0, 3.5, 3.0 ] }
          },
          "children": [
            {
              "name": "top",
              "from": [ 0.5, 3.0, 0.5 ],
              "to": [ 2.5, 3.5, 2.5 ],
              "rotationOrigin": [ 1.5, 3.0, 1.5 ],
              "faces": {
                "north": { "texture": "#brambleberry", "uv": [ 0.5, 2.0, 2.5, 2.5 ] },
                "east": { "texture": "#brambleberry", "uv": [ 0.0, 1.0, 2.0, 1.5 ] },
                "south": { "texture": "#brambleberry", "uv": [ 1.5, 2.5, 3.5, 3.0 ] },
                "west": { "texture": "#brambleberry", "uv": [ 1.0, 2.0, 3.0, 2.5 ] },
                "up": { "texture": "#brambleberry", "uv": [ 0.5, 0.0, 2.5, 2.0 ] },
                "down": { "texture": "#brambleberry", "uv": [ 0.0, 0.0, 2.0, 2.0 ], "enabled": false }
              }
            },
            {
              "name": "bottom",
              "from": [ 0.5, -0.5, 0.5 ],
              "to": [ 2.5, 0.0, 2.5 ],
              "rotationOrigin": [ 1.5, -0.5, 1.5 ],
              "faces": {
                "north": { "texture": "#brambleberry", "uv": [ 1.0, 2.5, 3.0, 3.0 ] },
                "east": { "texture": "#brambleberry", "uv": [ 1.0, 3.0, 3.0, 3.5 ] },
                "south": { "texture": "#brambleberry", "uv": [ 1.0, 2.5, 3.0, 3.0 ] },
                "west": { "texture": "#brambleberry", "uv": [ 0.5, 1.5, 2.5, 2.0 ] },
                "up": { "texture": "#brambleberry", "uv": [ 0.0, 0.0, 2.0, 2.0 ], "enabled": false },
                "down": { "texture": "#brambleberry", "uv": [ 1.0, 2.0, 3.0, 4.0 ] }
              }
            },
            {
              "name": "body2",
              "from": [ 0.0, 0.2, 0.0 ],
              "to": [ 3.0, 2.8, 3.0 ],
              "rotationOrigin": [ 1.5, 0.2, 1.5 ],
              "rotationY": -45.0,
              "faces": {
                "north": { "texture": "#brambleberry", "uv": [ 0.0, 0.0, 3.0, 2.5 ] },
                "east": { "texture": "#brambleberry", "uv": [ 0.0, 0.0, 3.0, 2.5 ] },
                "south": { "texture": "#brambleberry", "uv": [ 0.0, 0.0, 3.0, 2.5 ] },
                "west": { "texture": "#brambleberry", "uv": [ 0.0, 0.0, 3.0, 2.5 ] },
                "up": { "texture": "#brambleberry", "uv": [ 0.0, 0.0, 3.0, 3.0 ] },
                "down": { "texture": "#brambleberry", "uv": [ 0.0, 0.0, 3.0, 3.0 ] }
              }
            }
          ]
        },
        {
          "name": "body12",
          "from": [ -2.7, 1.6, -2.5 ],
          "to": [ 0.3, 4.6, 0.5 ],
          "rotationOrigin": [ -1.2, 1.6, -1.0 ],
          "rotationX": -45.0,
          "rotationZ": 45.0,
          "faces": {
            "north": { "texture": "#brambleberry", "uv": [ 0.0, 0.0, 3.0, 3.0 ] },
            "east": { "texture": "#brambleberry", "uv": [ 0.5, 0.0, 3.5, 3.0 ] },
            "south": { "texture": "#brambleberry", "uv": [ 0.5, 0.0, 3.5, 3.0 ] },
            "west": { "texture": "#brambleberry", "uv": [ 0.0, 0.0, 3.0, 3.0 ] },
            "up": { "texture": "#brambleberry", "uv": [ 0.5, 0.5, 3.5, 3.5 ] },
            "down": { "texture": "#brambleberry", "uv": [ 0.5, 0.0, 3.5, 3.0 ] }
          },
          "children": [
            {
              "name": "top13",
              "from": [ 0.5, 3.0, 0.5 ],
              "to": [ 2.5, 3.5, 2.5 ],
              "rotationOrigin": [ 1.5, 3.0, 1.5 ],
              "faces": {
                "north": { "texture": "#brambleberry", "uv": [ 0.5, 2.0, 2.5, 2.5 ] },
                "east": { "texture": "#brambleberry", "uv": [ 0.0, 1.0, 2.0, 1.5 ] },
                "south": { "texture": "#brambleberry", "uv": [ 1.5, 2.5, 3.5, 3.0 ] },
                "west": { "texture": "#brambleberry", "uv": [ 1.0, 2.0, 3.0, 2.5 ] },
                "up": { "texture": "#brambleberry", "uv": [ 0.5, 0.0, 2.5, 2.0 ] },
                "down": { "texture": "#brambleberry", "uv": [ 0.0, 0.0, 2.0, 2.0 ], "enabled": false }
              }
            },
            {
              "name": "bottom14",
              "from": [ 0.5, -0.5, 0.5 ],
              "to": [ 2.5, 0.0, 2.5 ],
              "rotationOrigin": [ 1.5, -0.5, 1.5 ],
              "faces": {
                "north": { "texture": "#brambleberry", "uv": [ 1.0, 2.5, 3.0, 3.0 ] },
                "east": { "texture": "#brambleberry", "uv": [ 1.0, 3.0, 3.0, 3.5 ] },
                "south": { "texture": "#brambleberry", "uv": [ 1.0, 2.5, 3.0, 3.0 ] },
                "west": { "texture": "#brambleberry", "uv": [ 0.5, 1.5, 2.5, 2.0 ] },
                "up": { "texture": "#brambleberry", "uv": [ 0.0, 0.0, 2.0, 2.0 ], "enabled": false },
                "down": { "texture": "#brambleberry", "uv": [ 1.0, 2.0, 3.0, 4.0 ] }
              }
            },
            {
              "name": "body20",
              "from": [ 0.0, 0.2, 0.0 ],
              "to": [ 3.0, 2.8, 3.0 ],
              "rotationOrigin": [ 1.5, 0.2, 1.5 ],
              "rotationY": -45.0,
              "faces": {
                "north": { "texture": "#brambleberry", "uv": [ 0.0, 0.0, 3.0, 2.5 ] },
                "east": { "texture": "#brambleberry", "uv": [ 0.0, 0.0, 3.0, 2.5 ] },
                "south": { "texture": "#brambleberry", "uv": [ 0.0, 0.0, 3.0, 2.5 ] },
                "west": { "texture": "#brambleberry", "uv": [ 0.0, 0.0, 3.0, 2.5 ] },
                "up": { "texture": "#brambleberry", "uv": [ 0.0, 0.0, 3.0, 3.0 ] },
                "down": { "texture": "#brambleberry", "uv": [ 0.0, 0.0, 3.0, 3.0 ] }
              }
            }
          ]
        },
        {
          "name": "body22",
          "from": [ -0.1, 1.0, -2.1 ],
          "to": [ 2.9, 4.0, 0.9 ],
          "rotationOrigin": [ 1.4, 1.0, -0.6 ],
          "rotationX": -45.0,
          "rotationY": -12.5,
          "rotationZ": -42.5,
          "faces": {
            "north": { "texture": "#brambleberry", "uv": [ 0.0, 0.0, 3.0, 3.0 ] },
            "east": { "texture": "#brambleberry", "uv": [ 0.5, 0.0, 3.5, 3.0 ] },
            "south": { "texture": "#brambleberry", "uv": [ 0.5, 0.0, 3.5, 3.0 ] },
            "west": { "texture": "#brambleberry", "uv": [ 0.0, 0.0, 3.0, 3.0 ] },
            "up": { "texture": "#brambleberry", "uv": [ 0.5, 0.5, 3.5, 3.5 ] },
            "down": { "texture": "#brambleberry", "uv": [ 0.5, 0.0, 3.5, 3.0 ] }
          },
          "children": [
            {
              "name": "top23",
              "from": [ 0.5, 3.0, 0.5 ],
              "to": [ 2.5, 3.5, 2.5 ],
              "rotationOrigin": [ 1.5, 3.0, 1.5 ],
              "faces": {
                "north": { "texture": "#brambleberry", "uv": [ 0.5, 2.0, 2.5, 2.5 ] },
                "east": { "texture": "#brambleberry", "uv": [ 0.0, 1.0, 2.0, 1.5 ] },
                "south": { "texture": "#brambleberry", "uv": [ 1.5, 2.5, 3.5, 3.0 ] },
                "west": { "texture": "#brambleberry", "uv": [ 1.0, 2.0, 3.0, 2.5 ] },
                "up": { "texture": "#brambleberry", "uv": [ 0.5, 0.0, 2.5, 2.0 ] },
                "down": { "texture": "#brambleberry", "uv": [ 0.0, 0.0, 2.0, 2.0 ], "enabled": false }
              }
            },
            {
              "name": "bottom24",
              "from": [ 0.5, -0.5, 0.5 ],
              "to": [ 2.5, 0.0, 2.5 ],
              "rotationOrigin": [ 1.5, -0.5, 1.5 ],
              "faces": {
                "north": { "texture": "#brambleberry", "uv": [ 1.0, 2.5, 3.0, 3.0 ] },
                "east": { "texture": "#brambleberry", "uv": [ 1.0, 3.0, 3.0, 3.5 ] },
                "south": { "texture": "#brambleberry", "uv": [ 1.0, 2.5, 3.0, 3.0 ] },
                "west": { "texture": "#brambleberry", "uv": [ 0.5, 1.5, 2.5, 2.0 ] },
                "up": { "texture": "#brambleberry", "uv": [ 0.0, 0.0, 2.0, 2.0 ], "enabled": false },
                "down": { "texture": "#brambleberry", "uv": [ 1.0, 2.0, 3.0, 4.0 ] }
              }
            },
            {
              "name": "body30",
              "from": [ 0.0, 0.2, 0.0 ],
              "to": [ 3.0, 2.8, 3.0 ],
              "rotationOrigin": [ 1.5, 0.2, 1.5 ],
              "rotationY": -45.0,
              "faces": {
                "north": { "texture": "#brambleberry", "uv": [ 0.0, 0.0, 3.0, 2.5 ] },
                "east": { "texture": "#brambleberry", "uv": [ 0.0, 0.0, 3.0, 2.5 ] },
                "south": { "texture": "#brambleberry", "uv": [ 0.0, 0.0, 3.0, 2.5 ] },
                "west": { "texture": "#brambleberry", "uv": [ 0.0, 0.0, 3.0, 2.5 ] },
                "up": { "texture": "#brambleberry", "uv": [ 0.0, 0.0, 3.0, 3.0 ] },
                "down": { "texture": "#brambleberry", "uv": [ 0.0, 0.0, 3.0, 3.0 ] }
              }
            }
          ]
        },
        {
          "name": "leaf1",
          "from": [ -1.5, 0.0, -3.8 ],
          "to": [ 1.5, 0.0, -1.3 ],
          "rotationOrigin": [ 0.0, 0.0, -2.55 ],
          "rotationX": 4.0,
          "rotationY": 1.0,
          "faces": {
            "north": { "texture": "#brambleberry", "uv": [ 4.5, 3.0, 7.5, 3.5 ], "enabled": false },
            "east": { "texture": "#brambleberry", "uv": [ 0.0, 0.0, 2.5, 0.5 ], "enabled": false },
            "south": { "texture": "#brambleberry", "uv": [ 0.0, 0.0, 3.0, 0.5 ], "enabled": false },
            "west": { "texture": "#brambleberry", "uv": [ 0.0, 0.0, 2.5, 0.5 ], "enabled": false },
            "up": { "texture": "#brambleberry", "uv": [ 4.5, 1.5, 7.5, 4.0 ] },
            "down": { "texture": "#brambleberry", "uv": [ 0.0, 0.0, 3.0, 2.5 ], "enabled": false }
          }
        },
        {
          "name": "leaf2",
          "from": [ 0.1, -0.01, -2.9 ],
          "to": [ 3.1, -0.01, -0.4 ],
          "rotationOrigin": [ 1.6, -0.01, -1.65 ],
          "rotationX": 4.0,
          "rotationY": -51.0,
          "faces": {
            "north": { "texture": "#brambleberry", "uv": [ 4.5, 3.0, 7.5, 3.5 ], "enabled": false },
            "east": { "texture": "#brambleberry", "uv": [ 0.0, 0.0, 2.5, 0.5 ], "enabled": false },
            "south": { "texture": "#brambleberry", "uv": [ 0.0, 0.0, 3.0, 0.5 ], "enabled": false },
            "west": { "texture": "#brambleberry", "uv": [ 0.0, 0.0, 2.5, 0.5 ], "enabled": false },
            "up": { "texture": "#brambleberry", "uv": [ 4.5, 1.5, 7.5, 4.0 ] },
            "down": { "texture": "#brambleberry", "uv": [ 0.0, 0.0, 3.0, 2.5 ], "enabled": false }
          }
        },
        {
          "name": "leaf3",
          "from": [ 0.5, -0.02, -1.0 ],
          "to": [ 3.5, -0.02, 1.5 ],
          "rotationOrigin": [ 2.0, -0.02, 0.25 ],
          "rotationX": 4.0,
          "rotationY": -99.0,
          "faces": {
            "north": { "texture": "#brambleberry", "uv": [ 4.5, 3.0, 7.5, 3.5 ], "enabled": false },
            "east": { "texture": "#brambleberry", "uv": [ 0.0, 0.0, 2.5, 0.5 ], "enabled": false },
            "south": { "texture": "#brambleberry", "uv": [ 0.0, 0.0, 3.0, 0.5 ], "enabled": false },
            "west": { "texture": "#brambleberry", "uv": [ 0.0, 0.0, 2.5, 0.5 ], "enabled": false },
            "up": { "texture": "#brambleberry", "uv": [ 4.5, 1.5, 7.5, 4.0 ] },
            "down": { "texture": "#brambleberry", "uv": [ 0.0, 0.0, 3.0, 2.5 ], "enabled": false }
          }
        },
        {
          "name": "leaf4",
          "from": [ -3.1, -0.01, -3.2 ],
          "to": [ -0.1, -0.01, -0.7 ],
          "rotationOrigin": [ -1.6, -0.01, -1.95 ],
          "rotationX": 4.0,
          "rotationY": -145.0,
          "faces": {
            "north": { "texture": "#brambleberry", "uv": [ 4.5, 3.0, 7.5, 3.5 ], "enabled": false },
            "east": { "texture": "#brambleberry", "uv": [ 0.0, 0.0, 2.5, 0.5 ], "enabled": false },
            "south": { "texture": "#brambleberry", "uv": [ 0.0, 0.0, 3.0, 0.5 ], "enabled": false },
            "west": { "texture": "#brambleberry", "uv": [ 0.0, 0.0, 2.5, 0.5 ], "enabled": false },
            "up": { "texture": "#brambleberry", "uv": [ 4.5, 1.5, 7.5, 4.0 ], "rotation": 180 },
            "down": { "texture": "#brambleberry", "uv": [ 0.0, 0.0, 3.0, 2.5 ], "enabled": false }
          }
        },
        {
          "name": "leaf5",
          "from": [ -3.5, -0.02, -1.2 ],
          "to": [ -0.5, -0.02, 1.3 ],
          "rotationOrigin": [ -2.0, -0.01, 0.05 ],
          "rotationX": 4.0,
          "rotationY": -82.0,
          "faces": {
            "north": { "texture": "#brambleberry", "uv": [ 4.5, 3.0, 7.5, 3.5 ], "enabled": false },
            "east": { "texture": "#brambleberry", "uv": [ 0.0, 0.0, 2.5, 0.5 ], "enabled": false },
            "south": { "texture": "#brambleberry", "uv": [ 0.0, 0.0, 3.0, 0.5 ], "enabled": false },
            "west": { "texture": "#brambleberry", "uv": [ 0.0, 0.0, 2.5, 0.5 ], "enabled": false },
            "up": { "texture": "#brambleberry", "uv": [ 4.5, 1.5, 7.5, 4.0 ], "rotation": 180 },
            "down": { "texture": "#brambleberry", "uv": [ 0.0, 0.0, 3.0, 2.5 ], "enabled": false }
          }
        },
        {
          "name": "leaf6",
          "from": [ -2.5, -0.01, 0.3 ],
          "to": [ 0.5, -0.01, 2.8 ],
          "rotationOrigin": [ -1.0, -0.01, 1.55 ],
          "rotationX": 4.0,
          "rotationY": -27.5,
          "faces": {
            "north": { "texture": "#brambleberry", "uv": [ 4.5, 3.0, 7.5, 3.5 ], "enabled": false },
            "east": { "texture": "#brambleberry", "uv": [ 0.0, 0.0, 2.5, 0.5 ], "enabled": false },
            "south": { "texture": "#brambleberry", "uv": [ 0.0, 0.0, 3.0, 0.5 ], "enabled": false },
            "west": { "texture": "#brambleberry", "uv": [ 0.0, 0.0, 2.5, 0.5 ], "enabled": false },
            "up": { "texture": "#brambleberry", "uv": [ 4.5, 1.5, 7.5, 4.0 ], "rotation": 180 },
            "down": { "texture": "#brambleberry", "uv": [ 0.0, 0.0, 3.0, 2.5 ], "enabled": false }
          }
        },
        {
          "name": "leaf7",
          "from": [ -0.9, -0.03, 0.2 ],
          "to": [ 2.1, -0.03, 2.7 ],
          "rotationOrigin": [ 0.6, -0.01, 1.45 ],
          "rotationX": 4.0,
          "rotationY": 12.5,
          "faces": {
            "north": { "texture": "#brambleberry", "uv": [ 4.5, 3.0, 7.5, 3.5 ], "enabled": false },
            "east": { "texture": "#brambleberry", "uv": [ 0.0, 0.0, 2.5, 0.5 ], "enabled": false },
            "south": { "texture": "#brambleberry", "uv": [ 0.0, 0.0, 3.0, 0.5 ], "enabled": false },
            "west": { "texture": "#brambleberry", "uv": [ 0.0, 0.0, 2.5, 0.5 ], "enabled": false },
            "up": { "texture": "#brambleberry", "uv": [ 4.5, 1.5, 7.5, 4.0 ], "rotation": 180 },
            "down": { "texture": "#brambleberry", "uv": [ 0.0, 0.0, 3.0, 2.5 ], "enabled": false }
          }
        },
        {
          "name": "leaf8",
          "from": [ -1.5, -0.03, -1.4 ],
          "to": [ 1.5, -0.03, 1.1 ],
          "rotationOrigin": [ 0.0, -0.01, -0.15 ],
          "rotationX": 4.0,
          "rotationY": 12.5,
          "faces": {
            "north": { "texture": "#brambleberry", "uv": [ 4.5, 3.0, 7.5, 3.5 ], "enabled": false },
            "east": { "texture": "#brambleberry", "uv": [ 0.0, 0.0, 2.5, 0.5 ], "enabled": false },
            "south": { "texture": "#brambleberry", "uv": [ 0.0, 0.0, 3.0, 0.5 ], "enabled": false },
            "west": { "texture": "#brambleberry", "uv": [ 0.0, 0.0, 2.5, 0.5 ], "enabled": false },
            "up": { "texture": "#brambleberry", "uv": [ 4.5, 1.5, 7.5, 4.0 ], "rotation": 180 },
            "down": { "texture": "#brambleberry", "uv": [ 0.0, 0.0, 3.0, 2.5 ], "enabled": false }
          }
        }
      ]
    }
  ]}